example_package_nagore_ainhoa4/__init__.py
example_package_nagore_ainhoa4/functions.py
example_package_nagore_ainhoa4-0.0.1.dist-info/METADATA
example_package_nagore_ainhoa4-0.0.1.dist-info/WHEEL
example_package_nagore_ainhoa4-0.0.1.dist-info/licenses/LICENSE
example_package_nagore_ainhoa4-0.0.1.dist-info/RECORD
